tsresolve/__init__.py
tsresolve/constants.py
tsresolve/event_parser.py
tsresolve/test_ts.py
tsresolve/time_stamp_resolver.py
tsresolve-0.6.dist-info/LICENSE
tsresolve-0.6.dist-info/METADATA
tsresolve-0.6.dist-info/WHEEL
tsresolve-0.6.dist-info/top_level.txt
tsresolve-0.6.dist-info/RECORD
