Metadata-Version: 2.1
Name: tsresolve
Version: 0.6
Summary: Natural language parsing of recurring events
Home-page: https://github.com/akhilkumard/tsresolve
Author: Akhil Kumar D
Author-email: akhilkumar.doppalapudi@gmail.com
License: MIT
Keywords: Natural language parsing of time stamps
Platform: UNKNOWN
Classifier: Natural Language :: English
Classifier: Topic :: Text Processing :: Linguistic
Classifier: License :: OSI Approved :: MIT License
Requires-Dist: parsedatetime
Requires-Dist: python-dateutil
